karaml
